xtag/__init__.py
xtag/xtag.py
xtag-0.0.1.dist-info/LICENSE.txt
xtag-0.0.1.dist-info/METADATA
xtag-0.0.1.dist-info/WHEEL
xtag-0.0.1.dist-info/top_level.txt
xtag-0.0.1.dist-info/RECORD
