Metadata-Version: 2.1
Name: xtag
Version: 0.0.1
Summary: A python model for easily wrapping strings into html/xml tags.
Home-page: https://github.com/iBiology/xtag/
Author: FEI YUAN
Author-email: yuanfeifuzzy@gmail.com
License: MIT
Project-URL: Documentation, https://ibiology.github.io/xtag/
Platform: any
Classifier: Development Status :: 4 - Beta
Classifier: Programming Language :: Python
License-File: LICENSE.txt
Requires-Dist: importlib-metadata
Requires-Dist: python-version (>"3.6")
Requires-Dist: pytest
Requires-Dist: pytest-cov
Provides-Extra: testing
Requires-Dist: setuptools ; extra == 'testing'
Requires-Dist: pytest ; extra == 'testing'
Requires-Dist: pytest-cov ; extra == 'testing'
